stackhut_common/__init__.py
stackhut_common/config.py
stackhut_common/utils.py
stackhut_common/commands.py
stackhut_common/runtime/__init__.py
stackhut_common/runtime/rpc.py
stackhut_common/runtime/runtime_server.py
stackhut_common/runtime/runner.py
stackhut_common/runtime/backends.py
stackhut_common/barrister/__init__.py
stackhut_common/barrister/runtime.py
stackhut_common/barrister/parser.py
stackhut_common/barrister/cythonplex3/Timing.py
stackhut_common/barrister/cythonplex3/DFA.py
stackhut_common/barrister/cythonplex3/__init__.py
stackhut_common/barrister/cythonplex3/Machines.py
stackhut_common/barrister/cythonplex3/Scanners.py
stackhut_common/barrister/cythonplex3/Transitions.py
stackhut_common/barrister/cythonplex3/Actions.py
stackhut_common/barrister/cythonplex3/Errors.py
stackhut_common/barrister/cythonplex3/Regexps.py
stackhut_common/barrister/cythonplex3/Lexicons.py
stackhut_common/barrister/cythonplex3/Traditional.py
stackhut_common-0.5.6.dist-info/pbr.json
stackhut_common-0.5.6.dist-info/metadata.json
stackhut_common-0.5.6.dist-info/top_level.txt
stackhut_common-0.5.6.dist-info/RECORD
stackhut_common-0.5.6.dist-info/WHEEL
stackhut_common-0.5.6.dist-info/DESCRIPTION.rst
stackhut_common-0.5.6.dist-info/METADATA
