Metadata-Version: 2.0
Name: stackhut-common
Version: 0.5.6
Summary: Run your software in the cloud
Home-page: https://github.com/stackhut/stackhut-common
Author: StackHut
Author-email: stackhut@stackhut.com
License: Apache
Keywords: stackhut
Platform: POSIX
Classifier: Development Status :: 2 - Pre-Alpha
Classifier: Intended Audience :: Developers
Classifier: Environment :: Console
Classifier: Natural Language :: English
Classifier: License :: OSI Approved :: Apache Software License
Classifier: Operating System :: OS Independent
Classifier: Programming Language :: Python
Classifier: Programming Language :: Python :: 3
Classifier: Programming Language :: Python :: 3.4
Classifier: Topic :: Software Development
Requires-Dist: sh
Requires-Dist: requests
Requires-Dist: PyYaml
Requires-Dist: colorlog
Requires-Dist: werkzeug
Requires-Dist: json-rpc
